openapi_client/__init__.py
openapi_client/api_client.py
openapi_client/api_response.py
openapi_client/configuration.py
openapi_client/exceptions.py
openapi_client/py.typed
openapi_client/rest.py
openapi_client/api/__init__.py
openapi_client/api/correos_recepcin_api.py
openapi_client/api/dian_api.py
openapi_client/api/documentos_equivalentes_electrnicos_api.py
openapi_client/api/documentos_soporte_electrnicos_api.py
openapi_client/api/empresas_api.py
openapi_client/api/envio_correo_electrnico_api.py
openapi_client/api/eventos_electrnicos_api.py
openapi_client/api/facturas_de_venta_electrnicas_api.py
openapi_client/api/nminas_electrnicas_api.py
openapi_client/api/notas_crdito_electrnicas_api.py
openapi_client/api/notas_dbito_electrnicas_api.py
openapi_client/api/reports_api.py
openapi_client/api/resoluciones_api.py
openapi_client/api/sets_de_pruebas_api.py
openapi_client/models/__init__.py
openapi_client/models/address_data_fe.py
openapi_client/models/adjust_payroll_request.py
openapi_client/models/associated_document.py
openapi_client/models/cancel_payroll200_response.py
openapi_client/models/cancel_payroll_request.py
openapi_client/models/company_invoice.py
openapi_client/models/contact_company.py
openapi_client/models/contact_customer.py
openapi_client/models/create_adjustment_note_equivalent_document200_response.py
openapi_client/models/create_adjustment_note_equivalent_document200_response_adjustment_note_equivalentdocument.py
openapi_client/models/create_adjustment_note_equivalent_document_request.py
openapi_client/models/create_adjustment_note_equivalent_document_request_customer.py
openapi_client/models/create_adjustment_note_equivalent_document_request_delivery.py
openapi_client/models/create_adjustment_note_equivalent_document_request_delivery_address.py
openapi_client/models/create_adjustment_note_equivalent_document_request_delivery_delivery_company.py
alegra_sdk_python-1.0.6.dist-info/LICENSE
alegra_sdk_python-1.0.6.dist-info/METADATA
alegra_sdk_python-1.0.6.dist-info/WHEEL
alegra_sdk_python-1.0.6.dist-info/top_level.txt
alegra_sdk_python-1.0.6.dist-info/RECORD
