Metadata-Version: 2.2
Name: alegra-sdk-python
Version: 1.0.6
Summary: API Alegra Proveedor Electrónico Colombia
Home-page: https://github.com/FernandoPiDi/alegra-python-sdk
Author: Duvan Fernando Pinto Diaz
Author-email: duvanpidi@hotmail.com
License: MIT
Keywords: OpenAPI,OpenAPI-Generator,API Alegra Proveedor Electrónico Colombia
License-File: LICENSE
Requires-Dist: urllib3<3.0.0,>=1.25.3
Requires-Dist: python-dateutil>=2.8.2
Requires-Dist: pydantic>=2
Requires-Dist: typing-extensions==4.10.0
Dynamic: author
Dynamic: author-email
Dynamic: description
Dynamic: description-content-type
Dynamic: home-page
Dynamic: keywords
Dynamic: license
Dynamic: requires-dist
Dynamic: summary
